alayalite/index.py
alayalite/client.py
alayalite/__init__.py
alayalite/common.py
alayalite/utils.py
alayalite/collection.py
alayalite/defaults.py
alayalite/_alayalitepy.cpython-38-darwin.so
alayalite/schema.py
alayalite/rag/embedder/jina_embedder.py
alayalite/rag/embedder/__init__.py
alayalite/rag/embedder/embedder.py
alayalite/rag/embedder/bge_embedder.py
alayalite/rag/embedder/multilingual_embedder.py
alayalite/rag/embedder/m3e_embedder.py
alayalite/rag/embedder/base.py
alayalite/rag/chunker/chunker.py
alayalite/rag/chunker/__init__.py
alayalite/rag/chunker/sentence_chunker.py
alayalite/rag/chunker/semantic_chunker.py
alayalite/rag/chunker/fix_size_chunker.py
alayalite/rag/chunker/base.py
alayalite/.dylibs/libomp.dylib
alayalite-0.1.1a1.dist-info/RECORD
alayalite-0.1.1a1.dist-info/WHEEL
alayalite-0.1.1a1.dist-info/METADATA
alayalite-0.1.1a1.dist-info/licenses/LICENSE
