Metadata-Version: 2.2
Name: alayalite
Version: 0.1.1a1
Summary: AlayaLite Python extension module
Author-Email: "AlayaDB.AI" <dev@alayadb.ai>
License: Apache-2.0
Project-URL: Homepage, https://github.com/AlayaDB-AI/AlayaLite
Requires-Python: >=3.8
Requires-Dist: pandas>=1.3.3
